opengridview
